{
    "name": "python3-sip",
    "buildsystem": "simple",
    "build-commands": [
        "pip3 install --verbose --exists-action=i --no-index --find-links=\"file://${PWD}\" --prefix=${FLATPAK_DEST} \"sip\" --no-build-isolation"
    ],
    "sources": [
        {
            "type": "file",
            "url": "https://files.pythonhosted.org/packages/b7/b9/c538f279a4e237a006a2c98387d081e9eb060d203d8ed34467cc0f0b9b53/packaging-26.0-py3-none-any.whl",
            "sha256": "b36f1fef9334a5588b4166f8bcd26a14e521f2b55e6b9de3aaa80d3ff7a37529",
            "x-checker-data": {
                "type": "pypi",
                "name": "packaging",
                "packagetype": "bdist_wheel"
            }
        },
        {
            "type": "file",
            "url": "https://files.pythonhosted.org/packages/1c/7d/136d2f521fa6d9b9921e41d141be605ad57f32a055ff7141ebd63b830bfc/sip-6.15.1-py3-none-any.whl",
            "sha256": "596cd4b306cf11de469f3f638b24c592763b2d8accb127170b0db95c530b0700",
            "x-checker-data": {
                "type": "pypi",
                "name": "sip",
                "packagetype": "bdist_wheel"
            }
        }
    ],
    "cleanup": [
        "*"
    ]
}