{
    "name": "python3-sip",
    "buildsystem": "simple",
    "build-commands": [
        "pip3 install --verbose --exists-action=i --no-index --find-links=\"file://${PWD}\" --prefix=${FLATPAK_DEST} \"sip\""
    ],
    "sources": [
        {
            "type": "file",
            "url": "https://files.pythonhosted.org/packages/08/aa/cc0199a5f0ad350994d660967a8efb233fe0416e4639146c089643407ce6/packaging-24.1-py3-none-any.whl",
            "sha256": "5b8f2217dbdbd2f7f384c41c628544e6d52f2d0f53c6d0c3ea61aa5d1d7ff124",
            "x-checker-data": {
                "type": "pypi",
                "name": "packaging",
                "packagetype": "bdist_wheel"
            }
        },
        {
            "type": "file",
            "url": "https://files.pythonhosted.org/packages/2d/32/0f3285a9d97918c43851b232212b1c61a46c24b7d115c9680d9dbf1a840c/sip-6.8.5-py3-none-any.whl",
            "sha256": "8308d31da6f3cb9425400c71c322d3cd8bf58ab45c8df079c17899bbef849c77",
            "x-checker-data": {
                "type": "pypi",
                "name": "sip",
                "packagetype": "bdist_wheel"
            }
        }
    ],
    "cleanup": [
        "*"
    ]
}